worker/__init__.py
worker/caoe.py
worker/celery.py
worker/celery_app.py
worker/celery_demo_tasks.py
worker/celeryconfig.py
worker/coroutine.py
worker/exception.py
worker/loop.py
worker/process.py
worker/thread.py
worker/util.py
worker/worker.py
worker-2018.3.3.dist-info/DESCRIPTION.rst
worker-2018.3.3.dist-info/METADATA
worker-2018.3.3.dist-info/RECORD
worker-2018.3.3.dist-info/WHEEL
worker-2018.3.3.dist-info/metadata.json
worker-2018.3.3.dist-info/top_level.txt
