Metadata-Version: 2.0
Name: worker
Version: 2018.3.3
Summary: store it
Home-page: https://github.com/pingf/worker.git
Author: Jesse MENG
Author-email: pingf0@gmail.com
License: BSD
Platform: any
Classifier: Intended Audience :: Developers
Classifier: License :: OSI Approved :: BSD License
Classifier: Operating System :: OS Independent
Classifier: Programming Language :: Python
Classifier: Topic :: Software Development :: Libraries :: Python Modules
Requires-Dist: termcc
Requires-Dist: loader
Requires-Dist: async-timeout
Requires-Dist: aiohttp
